iterm_theme_generator/__init__.py
iterm_theme_generator/__main__.py
iterm_theme_generator-0.3.8.data/data/LICENSE
iterm_theme_generator-0.3.8.data/data/README.rst
iterm_theme_generator-0.3.8.data/data/VERSION
iterm_theme_generator-0.3.8.data/data/requirements.txt
iterm_theme_generator-0.3.8.dist-info/LICENSE
iterm_theme_generator-0.3.8.dist-info/METADATA
iterm_theme_generator-0.3.8.dist-info/WHEEL
iterm_theme_generator-0.3.8.dist-info/entry_points.txt
iterm_theme_generator-0.3.8.dist-info/top_level.txt
iterm_theme_generator-0.3.8.dist-info/RECORD
