Metadata-Version: 2.1
Name: iterm-theme-generator
Version: 0.3.8
Summary: Generate iTerm2 colors from an image
Home-page: https://github.com/m4yers/iterm-theme-generator
Author: Artyom Goncharov
Author-email: m4yers@gmail.com
License: MIT
Keywords: iterm,iterm2,colors,theme,image,wallpaper
Platform: UNKNOWN
Classifier: Development Status :: 3 - Alpha
Classifier: Environment :: Web Environment
Classifier: Intended Audience :: Developers
Classifier: Topic :: Software Development :: Build Tools
Classifier: License :: OSI Approved :: MIT License
Classifier: Programming Language :: Python
Classifier: Programming Language :: Python :: 3
Requires-Python: >=3
License-File: LICENSE
Requires-Dist: colorz
